<?xml version="1.0" encoding="UTF-8"?>
<feature
      id="net.openchrom.msd.converter.supplier.pdf.feature"
      label="PDF Converter"
      version="1.4.0.qualifier"
      provider-name="http://www.openchrom.net">

   <description url="http://www.openchrom.net/plugins/converter/pdf/">
      This is a PDF chromatogram converter.
   </description>

   <copyright url="http://www.openchrom.net">
      Copyright (c) 2012, 2018 Lablicate GmbH.
   </copyright>

   <license url="http://www.openchrom.net">
      Copyright (c) 2012, 2018 Lablicate GmbH.
All rights reserved. This program and the accompanying materials
are made available under the terms of the Eclipse Public License
v1.0 which accompanies this distribution, and is available at
http://www.eclipse.org/legal/epl-v10.html
   </license>

   <requires>
      <import feature="net.openchrom.thirdpartylibraries.pdfjet.feature" version="2.81.0.qualifier"/>
   </requires>

   <plugin
         id="net.openchrom.msd.converter.supplier.pdf"
         download-size="0"
         install-size="0"
         version="0.0.0"
         unpack="false"/>

   <plugin
         id="net.openchrom.msd.converter.supplier.pdf.ui"
         download-size="0"
         install-size="0"
         version="0.0.0"
         unpack="false"/>

</feature>
